{
  "ComponentIndexes": {
    "componentProgressBar": 3,
    "Header": 4
  },
  "ControlUniqueIds": {
    "Access Control Points_DataCard1": 176,
    "Access Control Points_DataCard2": 151,
    "Access Control Points_DataCard2_1": 607,
    "Access Control Points_DataCard3": 376,
    "Acknowledgement_DataCard1": 47,
    "Acknowledgement_DataCard2": 389,
    "After Hours Access Required_DataCard1": 236,
    "After Hours Access Required_DataCard2": 126,
    "After Hours Access Required_DataCard2_1": 582,
    "After Hours Access Required_DataCard3": 358,
    "Alternate Sponsor_DataCard1": 271,
    "Alternate Sponsor_DataCard2": 86,
    "Alternate Sponsor_DataCard2_1": 542,
    "Alternate Sponsor_DataCard3": 320,
    "App": 1,
    "Assigned to Section_DataCard1": 166,
    "Assigned to Section_DataCard2": 136,
    "Assigned to Section_DataCard2_1": 592,
    "Assigned to Section_DataCard3": 381,
    "backAcknow": 51,
    "backEvent": 276,
    "backLongTerm": 186,
    "backReview": 156,
    "backReview_1": 612,
    "backVisitor": 241,
    "Body1": 291,
    "Button1": 402,
    "Button2_10": 396,
    "Button2_11": 398,
    "buttonNewRequest": 293,
    "buttonPreScreen": 36,
    "CAC Required?_DataCard1": 181,
    "CAC Required?_DataCard2": 146,
    "CAC Required?_DataCard2_1": 602,
    "CAC Required?_DataCard3": 373,
    "cbAcknow": 50,
    "checkAfterHours": 239,
    "Checkbox4": 285,
    "Circle2": 22,
    "Circle2_5": 5,
    "Circle2_6": 10,
    "Circle2_7": 15,
    "Circle2_9": 29,
    "collectionA": 28,
    "collectionESI": 4,
    "collectionLTAI/R": 14,
    "collectionR": 21,
    "collectionVI": 9,
    "ComboBox1_3": 400,
    "ComboBoxCheckBox": 282,
    "Company/Organization Phone Number_DataCard1": 216,
    "Company/Organization Phone Number_DataCard2": 116,
    "Company/Organization Phone Number_DataCard2_1": 572,
    "Company/Organization Phone Number_DataCard3": 345,
    "Company/Organization_DataCard1": 211,
    "Company/Organization_DataCard2": 111,
    "Company/Organization_DataCard2_1": 567,
    "Company/Organization_DataCard3": 342,
    "compHeaderRequest": 41,
    "componentProgressBar": 3,
    "Contract Number_DataCard1": 161,
    "Contract Number_DataCard2": 364,
    "DataCard1": 300,
    "DataCard2": 386,
    "DataCard3": 325,
    "DataCard4": 392,
    "DataCard5": 395,
    "DataCard6": 361,
    "DataCard7": 397,
    "DataCardKey1": 49,
    "DataCardKey10": 203,
    "DataCardKey11": 223,
    "DataCardKey12": 213,
    "DataCardKey13": 218,
    "DataCardKey14": 228,
    "DataCardKey15": 233,
    "DataCardKey16": 238,
    "DataCardKey17": 163,
    "DataCardKey18": 168,
    "DataCardKey19": 173,
    "DataCardKey2": 248,
    "DataCardKey20": 178,
    "DataCardKey21": 183,
    "DataCardKey22": 208,
    "DataCardKey23": 63,
    "DataCardKey23_1": 519,
    "DataCardKey24": 68,
    "DataCardKey24_1": 524,
    "DataCardKey25": 73,
    "DataCardKey25_1": 529,
    "DataCardKey26": 58,
    "DataCardKey26_1": 514,
    "DataCardKey27": 78,
    "DataCardKey27_1": 534,
    "DataCardKey28": 83,
    "DataCardKey28_1": 539,
    "DataCardKey29": 88,
    "DataCardKey29_1": 544,
    "DataCardKey3": 253,
    "DataCardKey30": 93,
    "DataCardKey30_1": 549,
    "DataCardKey31": 98,
    "DataCardKey31_1": 554,
    "DataCardKey32": 103,
    "DataCardKey32_1": 559,
    "DataCardKey33": 108,
    "DataCardKey33_1": 564,
    "DataCardKey34": 113,
    "DataCardKey34_1": 569,
    "DataCardKey35": 118,
    "DataCardKey35_1": 574,
    "DataCardKey36": 123,
    "DataCardKey36_1": 579,
    "DataCardKey37": 128,
    "DataCardKey37_1": 584,
    "DataCardKey38": 133,
    "DataCardKey38_1": 589,
    "DataCardKey39": 138,
    "DataCardKey39_1": 594,
    "DataCardKey4": 258,
    "DataCardKey40": 143,
    "DataCardKey40_1": 599,
    "DataCardKey41": 148,
    "DataCardKey41_1": 604,
    "DataCardKey42": 153,
    "DataCardKey42_1": 609,
    "DataCardKey43": 307,
    "DataCardKey44": 310,
    "DataCardKey45": 314,
    "DataCardKey46": 318,
    "DataCardKey47": 322,
    "DataCardKey48": 329,
    "DataCardKey49": 332,
    "DataCardKey5": 263,
    "DataCardKey50": 335,
    "DataCardKey51": 339,
    "DataCardKey52": 343,
    "DataCardKey53": 346,
    "DataCardKey54": 350,
    "DataCardKey55": 355,
    "DataCardKey56": 359,
    "DataCardKey57": 365,
    "DataCardKey58": 383,
    "DataCardKey59": 368,
    "DataCardKey6": 268,
    "DataCardKey60": 371,
    "DataCardKey61": 374,
    "DataCardKey62": 378,
    "DataCardKey63": 390,
    "DataCardKey69": 304,
    "DataCardKey7": 273,
    "DataCardKey8": 193,
    "DataCardKey9": 198,
    "DataCardValue1": 308,
    "DataCardValue10": 204,
    "DataCardValue11": 224,
    "DataCardValue12": 214,
    "DataCardValue13": 219,
    "DataCardValue14": 229,
    "DataCardValue15": 174,
    "DataCardValue16": 311,
    "DataCardValue17": 179,
    "DataCardValue18": 184,
    "DataCardValue19": 209,
    "DataCardValue2": 249,
    "DataCardValue20": 64,
    "DataCardValue20_1": 520,
    "DataCardValue21": 69,
    "DataCardValue21_1": 525,
    "DataCardValue22": 74,
    "DataCardValue22_1": 530,
    "DataCardValue23": 59,
    "DataCardValue23_1": 515,
    "DataCardValue24": 79,
    "DataCardValue24_1": 535,
    "DataCardValue25": 84,
    "DataCardValue25_1": 540,
    "DataCardValue26": 89,
    "DataCardValue26_1": 545,
    "DataCardValue27": 94,
    "DataCardValue27_1": 550,
    "DataCardValue28": 99,
    "DataCardValue28_1": 555,
    "DataCardValue29": 104,
    "DataCardValue29_1": 560,
    "DataCardValue3": 164,
    "DataCardValue30": 109,
    "DataCardValue30_1": 565,
    "DataCardValue31": 114,
    "DataCardValue31_1": 570,
    "DataCardValue32": 119,
    "DataCardValue32_1": 575,
    "DataCardValue33": 124,
    "DataCardValue33_1": 580,
    "DataCardValue34": 129,
    "DataCardValue34_1": 585,
    "DataCardValue35": 134,
    "DataCardValue35_1": 590,
    "DataCardValue36": 139,
    "DataCardValue36_1": 595,
    "DataCardValue37": 144,
    "DataCardValue37_1": 600,
    "DataCardValue38": 149,
    "DataCardValue38_1": 605,
    "DataCardValue39": 154,
    "DataCardValue39_1": 610,
    "DataCardValue4": 169,
    "DataCardValue40": 315,
    "DataCardValue41": 319,
    "DataCardValue42": 323,
    "DataCardValue43": 330,
    "DataCardValue44": 333,
    "DataCardValue45": 336,
    "DataCardValue46": 340,
    "DataCardValue47": 344,
    "DataCardValue48": 347,
    "DataCardValue49": 351,
    "DataCardValue5": 264,
    "DataCardValue50": 356,
    "DataCardValue51": 360,
    "DataCardValue52": 366,
    "DataCardValue53": 384,
    "DataCardValue54": 369,
    "DataCardValue55": 372,
    "DataCardValue56": 375,
    "DataCardValue57": 379,
    "DataCardValue58": 391,
    "DataCardValue6": 269,
    "DataCardValue64": 305,
    "DataCardValue7": 274,
    "DataCardValue8": 194,
    "DataCardValue9": 199,
    "Days a Week Working at MCTSSA_DataCard1": 231,
    "Days a Week Working at MCTSSA_DataCard2": 101,
    "Days a Week Working at MCTSSA_DataCard2_1": 557,
    "Days a Week Working at MCTSSA_DataCard3": 348,
    "dcDaysAWeek": 234,
    "dcEndDate": 259,
    "dcStartDate": 254,
    "ddDateFilter": 281,
    "EDIP_DataCard1": 171,
    "EDIP_DataCard2": 141,
    "EDIP_DataCard2_1": 597,
    "EDIP_DataCard3": 367,
    "Email_DataCard1": 206,
    "Email_DataCard2": 131,
    "Email_DataCard2_1": 587,
    "Email_DataCard3": 370,
    "ErrorMessage1": 316,
    "ErrorMessage10": 205,
    "ErrorMessage11": 225,
    "ErrorMessage12": 215,
    "ErrorMessage13": 220,
    "ErrorMessage14": 230,
    "ErrorMessage15": 235,
    "ErrorMessage16": 240,
    "ErrorMessage17": 165,
    "ErrorMessage18": 170,
    "ErrorMessage19": 175,
    "ErrorMessage2": 250,
    "ErrorMessage20": 180,
    "ErrorMessage21": 185,
    "ErrorMessage22": 210,
    "ErrorMessage23": 65,
    "ErrorMessage23_1": 521,
    "ErrorMessage24": 70,
    "ErrorMessage24_1": 526,
    "ErrorMessage25": 75,
    "ErrorMessage25_1": 531,
    "ErrorMessage26": 60,
    "ErrorMessage26_1": 516,
    "ErrorMessage27": 80,
    "ErrorMessage27_1": 536,
    "ErrorMessage28": 85,
    "ErrorMessage28_1": 541,
    "ErrorMessage29": 90,
    "ErrorMessage29_1": 546,
    "ErrorMessage3": 255,
    "ErrorMessage30": 95,
    "ErrorMessage30_1": 551,
    "ErrorMessage31": 100,
    "ErrorMessage31_1": 556,
    "ErrorMessage32": 105,
    "ErrorMessage32_1": 561,
    "ErrorMessage33": 110,
    "ErrorMessage33_1": 566,
    "ErrorMessage34": 115,
    "ErrorMessage34_1": 571,
    "ErrorMessage35": 120,
    "ErrorMessage35_1": 576,
    "ErrorMessage36": 125,
    "ErrorMessage36_1": 581,
    "ErrorMessage37": 130,
    "ErrorMessage37_1": 586,
    "ErrorMessage38": 135,
    "ErrorMessage38_1": 591,
    "ErrorMessage39": 140,
    "ErrorMessage39_1": 596,
    "ErrorMessage4": 260,
    "ErrorMessage40": 145,
    "ErrorMessage40_1": 601,
    "ErrorMessage41": 150,
    "ErrorMessage41_1": 606,
    "ErrorMessage42": 155,
    "ErrorMessage42_1": 611,
    "ErrorMessage43": 324,
    "ErrorMessage44": 341,
    "ErrorMessage45": 352,
    "ErrorMessage46": 357,
    "ErrorMessage47": 385,
    "ErrorMessage48": 380,
    "ErrorMessage5": 265,
    "ErrorMessage6": 270,
    "ErrorMessage7": 275,
    "ErrorMessage8": 195,
    "ErrorMessage9": 200,
    "First Name_DataCard1": 191,
    "First Name_DataCard2": 61,
    "First Name_DataCard2_1": 517,
    "First Name_DataCard3": 328,
    "formAcknow": 46,
    "formEvent": 245,
    "formLongTerm": 160,
    "formReview": 55,
    "formReview_1": 511,
    "formSecurity": 299,
    "formVisitor": 190,
    "galleryCheckBox": 283,
    "galleryRequests": 286,
    "galleryTemplate1": 287,
    "galleryTemplate6": 284,
    "Group1": 39,
    "Header": 32,
    "Icon2_3": 401,
    "iconA_1": 30,
    "iconA_2": 24,
    "iconESI_1": 6,
    "iconLTAI_1": 16,
    "iconR_1": 23,
    "iconR_2": 17,
    "iconVI_1": 11,
    "Image1": 34,
    "Label1": 403,
    "Label2": 301,
    "Label2_1": 326,
    "Label2_3": 387,
    "Label2_4": 393,
    "Label2_5": 362,
    "labelAcknow": 45,
    "labelEvent": 244,
    "labelLongTerm": 159,
    "labelNewEventName_15": 13,
    "labelNewEventName_17": 19,
    "labelNewEventName_18": 20,
    "labelNewEventName_19": 26,
    "labelNewEventName_20": 27,
    "labelNewEventName_21": 31,
    "labelNewEventName_6": 8,
    "labelReview": 54,
    "labelReview_1": 510,
    "labelSecurity": 298,
    "labelVisitor": 189,
    "Last Name_DataCard1": 201,
    "Last Name_DataCard2": 71,
    "Last Name_DataCard2_1": 527,
    "Last Name_DataCard3": 334,
    "Loading Label": 37,
    "Middle Name_DataCard1": 196,
    "Middle Name_DataCard2": 66,
    "Middle Name_DataCard2_1": 522,
    "Middle Name_DataCard3": 331,
    "modalFloatRequest": 43,
    "modalFloatSecurity": 296,
    "modalRequest": 42,
    "modalSecurity": 295,
    "nextAcknow": 52,
    "NextArrow1": 289,
    "nextEvent": 277,
    "nextLongTerm": 187,
    "nextReview": 157,
    "nextReview_1": 613,
    "nextVisitor": 242,
    "pageAcknow": 44,
    "pageEvent": 243,
    "pageLongTerm": 158,
    "pageReview": 53,
    "pageReview_1": 509,
    "pageSecurity": 297,
    "pageVisitor": 188,
    "pbRequest": 278,
    "Rank/Grade_DataCard1": 221,
    "Rank/Grade_DataCard2": 106,
    "Rank/Grade_DataCard2_1": 562,
    "Rank/Grade_DataCard3": 337,
    "Rectangle2": 302,
    "Rectangle2_1": 327,
    "Rectangle2_3": 388,
    "Rectangle2_4": 394,
    "Rectangle2_5": 363,
    "rectangleNewEventNameStatusBar_11": 12,
    "rectangleNewEventNameStatusBar_12": 18,
    "rectangleNewEventNameStatusBar_13": 25,
    "rectangleNewEventNameStatusBar_5": 7,
    "Round Header": 33,
    "Screen1": 294,
    "screenPre": 35,
    "screenRequest": 40,
    "searchBarRequest": 280,
    "searchIconRequest": 279,
    "Separator1": 292,
    "Sponsor Phone Number_DataCard1": 266,
    "Sponsor Phone Number_DataCard2": 81,
    "Sponsor Phone Number_DataCard2_1": 537,
    "Sponsor Phone Number_DataCard3": 317,
    "Sponsor_DataCard1": 261,
    "Sponsor_DataCard2": 76,
    "Sponsor_DataCard2_1": 532,
    "Sponsor_DataCard3": 312,
    "StarVisible1": 48,
    "StarVisible10": 202,
    "StarVisible11": 222,
    "StarVisible12": 212,
    "StarVisible13": 217,
    "StarVisible14": 227,
    "StarVisible15": 232,
    "StarVisible16": 237,
    "StarVisible17": 162,
    "StarVisible18": 167,
    "StarVisible19": 172,
    "StarVisible2": 247,
    "StarVisible20": 177,
    "StarVisible21": 182,
    "StarVisible22": 207,
    "StarVisible23": 62,
    "StarVisible23_1": 518,
    "StarVisible24": 67,
    "StarVisible24_1": 523,
    "StarVisible25": 72,
    "StarVisible25_1": 528,
    "StarVisible26": 57,
    "StarVisible26_1": 513,
    "StarVisible27": 77,
    "StarVisible27_1": 533,
    "StarVisible28": 82,
    "StarVisible28_1": 538,
    "StarVisible29": 87,
    "StarVisible29_1": 543,
    "StarVisible3": 252,
    "StarVisible30": 92,
    "StarVisible30_1": 548,
    "StarVisible31": 97,
    "StarVisible31_1": 553,
    "StarVisible32": 102,
    "StarVisible32_1": 558,
    "StarVisible33": 107,
    "StarVisible33_1": 563,
    "StarVisible34": 112,
    "StarVisible34_1": 568,
    "StarVisible35": 117,
    "StarVisible35_1": 573,
    "StarVisible36": 122,
    "StarVisible36_1": 578,
    "StarVisible37": 127,
    "StarVisible37_1": 583,
    "StarVisible38": 132,
    "StarVisible38_1": 588,
    "StarVisible39": 137,
    "StarVisible39_1": 593,
    "StarVisible4": 257,
    "StarVisible40": 142,
    "StarVisible40_1": 598,
    "StarVisible41": 147,
    "StarVisible41_1": 603,
    "StarVisible42": 152,
    "StarVisible42_1": 608,
    "StarVisible43": 313,
    "StarVisible44": 321,
    "StarVisible45": 338,
    "StarVisible46": 349,
    "StarVisible47": 354,
    "StarVisible48": 382,
    "StarVisible49": 377,
    "StarVisible5": 262,
    "StarVisible6": 267,
    "StarVisible7": 272,
    "StarVisible8": 192,
    "StarVisible9": 197,
    "Subtitle1": 290,
    "timer": 38,
    "Title_DataCard1": 246,
    "Title_DataCard2": 56,
    "Title_DataCard2_1": 512,
    "Title_DataCard4": 303,
    "Title1": 288,
    "txt_Denied_3": 399,
    "Type of Visit_DataCard1": 226,
    "Type of Visit_DataCard2": 121,
    "Type of Visit_DataCard2_1": 577,
    "Type of Visit_DataCard3": 353,
    "Visit End Date_DataCard1": 256,
    "Visit End Date_DataCard2": 96,
    "Visit End Date_DataCard2_1": 552,
    "Visit End Date_DataCard3": 309,
    "Visit Start Date_DataCard1": 251,
    "Visit Start Date_DataCard2": 91,
    "Visit Start Date_DataCard2_1": 547,
    "Visit Start Date_DataCard3": 306
  },
  "FunctionParamsInvariantScripts": {},
  "FunctionParamsInvariantScriptsOnInstances": {},
  "HeaderLastSavedDateTimeUTC": "07/05/2022 22:35:04",
  "IsLegacyComponentAllowGlobalScopeCase": false,
  "LocalConnectionIDReferences": {
    "17ba9056-a80f-4186-8daa-c0ccc989b864": "\"/providers/microsoft.powerapps/apis/shared_sharepointonline/connections/2e24395df0824c8fb53e52c89dcf5850\"",
    "550890c1-4cf8-4ce2-b7ed-dc900d503f31": "\"/providers/microsoft.powerapps/apis/shared_office365users/connections/07848a26627d4e0abe3201ac5634c0b0\"",
    "886c7fe8-664d-4a54-b513-dd974ed45f29": "\"/providers/microsoft.powerapps/apis/shared_office365groups/connections/09e4ba13cc184aeda3a47b4fd9e1e2fc\"",
    "8a4b6060-0c76-4743-acd4-c7c31205c369": "\"/providers/microsoft.powerapps/apis/shared_office365/connections/02b54ee00e5243cb85bbf44535562f22\"",
    "dd808c08-e4fa-4f05-9452-2ef6940db4f8": "\"/providers/microsoft.powerapps/apis/shared_sharepointonline/connections/2e24395df0824c8fb53e52c89dcf5850\""
  },
  "LocalDatabaseReferencesAsEmpty": false,
  "LocalResourceFileNames": {
    "Marine Corps Tactical Systems Support Activity _MCTSSA": "0001.png"
  },
  "LocalResourceRootPaths": {
    "Marine Corps Tactical Systems Support Activity _MCTSSA": "https://docserverpwaprodeus.blob.core.windows.net/e6838688-6480-4104-be90-cd050c9f439c-1/resource/Assets0Images00001.png?sv=2017-04-17&sr=b&sig=40QpFbYaQd4KR464fvaCxh6pGbv4AWGO2VnXApWqOew%3D&spr=https&se=2022-07-06T21%3A52%3A58Z&sp=r"
  },
  "OldLogoFileName": "logo.jpg",
  "OrderComponentMetadata": {
    "d5564032f2ee43308e8fdaf8819fb889": 1,
    "dbd607af812e46be9d29858798df077d": 0
  },
  "OrderComponentTemplate": {
    "d5564032f2ee43308e8fdaf8819fb889": 1,
    "dbd607af812e46be9d29858798df077d": 0
  },
  "OrderDataSource": {
    "colApprovedFilter": 8,
    "colTimeFilter": 9,
    "ComboBoxSample": 3,
    "CustomGallerySample": 4,
    "DropDownSample": 5,
    "Office365Groups": 0,
    "Office365Outlook": 1,
    "Office365Users": 2,
    "Security": 6,
    "VisitorRequest": 7
  },
  "OrderGroupControls": {
    "Group1": {
      "buttonPreScreen": 0,
      "Loading Label": 2,
      "timer": 1
    }
  },
  "OrderPcfTemplate": {},
  "OrderTemplate": {},
  "OrderXMLTemplate": {
    "button": 0,
    "checkbox": 6,
    "circle": 12,
    "combobox": 9,
    "datepicker": 10,
    "dropdown": 14,
    "form": 5,
    "formViewer": 16,
    "gallery": 15,
    "groupContainer": 4,
    "icon": 7,
    "image": 3,
    "label": 1,
    "rectangle": 13,
    "text": 8,
    "timer": 2,
    "toggleSwitch": 11
  },
  "PublishOrderIndices": {
    "Access Control Points_DataCard1": 139,
    "Access Control Points_DataCard2": 114,
    "Access Control Points_DataCard2_1": 339,
    "Access Control Points_DataCard3": 445,
    "Acknowledgement_DataCard1": 10,
    "Acknowledgement_DataCard2": 458,
    "After Hours Access Required_DataCard1": 199,
    "After Hours Access Required_DataCard2": 89,
    "After Hours Access Required_DataCard2_1": 314,
    "After Hours Access Required_DataCard3": 427,
    "Alternate Sponsor_DataCard1": 234,
    "Alternate Sponsor_DataCard2": 49,
    "Alternate Sponsor_DataCard2_1": 274,
    "Alternate Sponsor_DataCard3": 389,
    "App": 0,
    "Assigned to Section_DataCard1": 129,
    "Assigned to Section_DataCard2": 99,
    "Assigned to Section_DataCard2_1": 324,
    "Assigned to Section_DataCard3": 450,
    "backAcknow": 14,
    "backEvent": 239,
    "backLongTerm": 149,
    "backReview": 119,
    "backReview_1": 344,
    "backVisitor": 204,
    "Body1": 361,
    "Button1": 355,
    "Button2_10": 465,
    "Button2_11": 467,
    "buttonNewRequest": 363,
    "buttonPreScreen": 0,
    "CAC Required?_DataCard1": 144,
    "CAC Required?_DataCard2": 109,
    "CAC Required?_DataCard2_1": 334,
    "CAC Required?_DataCard3": 442,
    "cbAcknow": 13,
    "checkAfterHours": 202,
    "Checkbox4": 354,
    "Circle2": 489,
    "Circle2_5": 472,
    "Circle2_6": 477,
    "Circle2_7": 482,
    "Circle2_9": 496,
    "collectionA": 495,
    "collectionESI": 471,
    "collectionLTAI/R": 481,
    "collectionR": 488,
    "collectionVI": 476,
    "ComboBox1_3": 469,
    "ComboBoxCheckBox": 351,
    "Company/Organization Phone Number_DataCard1": 179,
    "Company/Organization Phone Number_DataCard2": 79,
    "Company/Organization Phone Number_DataCard2_1": 304,
    "Company/Organization Phone Number_DataCard3": 414,
    "Company/Organization_DataCard1": 174,
    "Company/Organization_DataCard2": 74,
    "Company/Organization_DataCard2_1": 299,
    "Company/Organization_DataCard3": 411,
    "compHeaderRequest": 4,
    "componentProgressBar": 1,
    "Contract Number_DataCard1": 124,
    "Contract Number_DataCard2": 433,
    "DataCard1": 369,
    "DataCard2": 455,
    "DataCard3": 394,
    "DataCard4": 461,
    "DataCard5": 464,
    "DataCard6": 430,
    "DataCard7": 466,
    "DataCardKey1": 12,
    "DataCardKey10": 166,
    "DataCardKey11": 186,
    "DataCardKey12": 176,
    "DataCardKey13": 181,
    "DataCardKey14": 191,
    "DataCardKey15": 196,
    "DataCardKey16": 201,
    "DataCardKey17": 126,
    "DataCardKey18": 131,
    "DataCardKey19": 136,
    "DataCardKey2": 211,
    "DataCardKey20": 141,
    "DataCardKey21": 146,
    "DataCardKey22": 171,
    "DataCardKey23": 26,
    "DataCardKey23_1": 251,
    "DataCardKey24": 31,
    "DataCardKey24_1": 256,
    "DataCardKey25": 36,
    "DataCardKey25_1": 261,
    "DataCardKey26": 21,
    "DataCardKey26_1": 246,
    "DataCardKey27": 41,
    "DataCardKey27_1": 266,
    "DataCardKey28": 46,
    "DataCardKey28_1": 271,
    "DataCardKey29": 51,
    "DataCardKey29_1": 276,
    "DataCardKey3": 216,
    "DataCardKey30": 56,
    "DataCardKey30_1": 281,
    "DataCardKey31": 61,
    "DataCardKey31_1": 286,
    "DataCardKey32": 66,
    "DataCardKey32_1": 291,
    "DataCardKey33": 71,
    "DataCardKey33_1": 296,
    "DataCardKey34": 76,
    "DataCardKey34_1": 301,
    "DataCardKey35": 81,
    "DataCardKey35_1": 306,
    "DataCardKey36": 86,
    "DataCardKey36_1": 311,
    "DataCardKey37": 91,
    "DataCardKey37_1": 316,
    "DataCardKey38": 96,
    "DataCardKey38_1": 321,
    "DataCardKey39": 101,
    "DataCardKey39_1": 326,
    "DataCardKey4": 221,
    "DataCardKey40": 106,
    "DataCardKey40_1": 331,
    "DataCardKey41": 111,
    "DataCardKey41_1": 336,
    "DataCardKey42": 116,
    "DataCardKey42_1": 341,
    "DataCardKey43": 376,
    "DataCardKey44": 379,
    "DataCardKey45": 383,
    "DataCardKey46": 387,
    "DataCardKey47": 391,
    "DataCardKey48": 398,
    "DataCardKey49": 401,
    "DataCardKey5": 226,
    "DataCardKey50": 404,
    "DataCardKey51": 408,
    "DataCardKey52": 412,
    "DataCardKey53": 415,
    "DataCardKey54": 419,
    "DataCardKey55": 424,
    "DataCardKey56": 428,
    "DataCardKey57": 434,
    "DataCardKey58": 452,
    "DataCardKey59": 437,
    "DataCardKey6": 231,
    "DataCardKey60": 440,
    "DataCardKey61": 443,
    "DataCardKey62": 447,
    "DataCardKey63": 459,
    "DataCardKey69": 373,
    "DataCardKey7": 236,
    "DataCardKey8": 156,
    "DataCardKey9": 161,
    "DataCardValue1": 377,
    "DataCardValue10": 167,
    "DataCardValue11": 187,
    "DataCardValue12": 177,
    "DataCardValue13": 182,
    "DataCardValue14": 192,
    "DataCardValue15": 137,
    "DataCardValue16": 380,
    "DataCardValue17": 142,
    "DataCardValue18": 147,
    "DataCardValue19": 172,
    "DataCardValue2": 212,
    "DataCardValue20": 27,
    "DataCardValue20_1": 252,
    "DataCardValue21": 32,
    "DataCardValue21_1": 257,
    "DataCardValue22": 37,
    "DataCardValue22_1": 262,
    "DataCardValue23": 22,
    "DataCardValue23_1": 247,
    "DataCardValue24": 42,
    "DataCardValue24_1": 267,
    "DataCardValue25": 47,
    "DataCardValue25_1": 272,
    "DataCardValue26": 52,
    "DataCardValue26_1": 277,
    "DataCardValue27": 57,
    "DataCardValue27_1": 282,
    "DataCardValue28": 62,
    "DataCardValue28_1": 287,
    "DataCardValue29": 67,
    "DataCardValue29_1": 292,
    "DataCardValue3": 127,
    "DataCardValue30": 72,
    "DataCardValue30_1": 297,
    "DataCardValue31": 77,
    "DataCardValue31_1": 302,
    "DataCardValue32": 82,
    "DataCardValue32_1": 307,
    "DataCardValue33": 87,
    "DataCardValue33_1": 312,
    "DataCardValue34": 92,
    "DataCardValue34_1": 317,
    "DataCardValue35": 97,
    "DataCardValue35_1": 322,
    "DataCardValue36": 102,
    "DataCardValue36_1": 327,
    "DataCardValue37": 107,
    "DataCardValue37_1": 332,
    "DataCardValue38": 112,
    "DataCardValue38_1": 337,
    "DataCardValue39": 117,
    "DataCardValue39_1": 342,
    "DataCardValue4": 132,
    "DataCardValue40": 384,
    "DataCardValue41": 388,
    "DataCardValue42": 392,
    "DataCardValue43": 399,
    "DataCardValue44": 402,
    "DataCardValue45": 405,
    "DataCardValue46": 409,
    "DataCardValue47": 413,
    "DataCardValue48": 416,
    "DataCardValue49": 420,
    "DataCardValue5": 227,
    "DataCardValue50": 425,
    "DataCardValue51": 429,
    "DataCardValue52": 435,
    "DataCardValue53": 453,
    "DataCardValue54": 438,
    "DataCardValue55": 441,
    "DataCardValue56": 444,
    "DataCardValue57": 448,
    "DataCardValue58": 460,
    "DataCardValue6": 232,
    "DataCardValue64": 374,
    "DataCardValue7": 237,
    "DataCardValue8": 157,
    "DataCardValue9": 162,
    "Days a Week Working at MCTSSA_DataCard1": 194,
    "Days a Week Working at MCTSSA_DataCard2": 64,
    "Days a Week Working at MCTSSA_DataCard2_1": 289,
    "Days a Week Working at MCTSSA_DataCard3": 417,
    "dcDaysAWeek": 197,
    "dcEndDate": 222,
    "dcStartDate": 217,
    "ddDateFilter": 349,
    "EDIP_DataCard1": 134,
    "EDIP_DataCard2": 104,
    "EDIP_DataCard2_1": 329,
    "EDIP_DataCard3": 436,
    "Email_DataCard1": 169,
    "Email_DataCard2": 94,
    "Email_DataCard2_1": 319,
    "Email_DataCard3": 439,
    "ErrorMessage1": 385,
    "ErrorMessage10": 168,
    "ErrorMessage11": 188,
    "ErrorMessage12": 178,
    "ErrorMessage13": 183,
    "ErrorMessage14": 193,
    "ErrorMessage15": 198,
    "ErrorMessage16": 203,
    "ErrorMessage17": 128,
    "ErrorMessage18": 133,
    "ErrorMessage19": 138,
    "ErrorMessage2": 213,
    "ErrorMessage20": 143,
    "ErrorMessage21": 148,
    "ErrorMessage22": 173,
    "ErrorMessage23": 28,
    "ErrorMessage23_1": 253,
    "ErrorMessage24": 33,
    "ErrorMessage24_1": 258,
    "ErrorMessage25": 38,
    "ErrorMessage25_1": 263,
    "ErrorMessage26": 23,
    "ErrorMessage26_1": 248,
    "ErrorMessage27": 43,
    "ErrorMessage27_1": 268,
    "ErrorMessage28": 48,
    "ErrorMessage28_1": 273,
    "ErrorMessage29": 53,
    "ErrorMessage29_1": 278,
    "ErrorMessage3": 218,
    "ErrorMessage30": 58,
    "ErrorMessage30_1": 283,
    "ErrorMessage31": 63,
    "ErrorMessage31_1": 288,
    "ErrorMessage32": 68,
    "ErrorMessage32_1": 293,
    "ErrorMessage33": 73,
    "ErrorMessage33_1": 298,
    "ErrorMessage34": 78,
    "ErrorMessage34_1": 303,
    "ErrorMessage35": 83,
    "ErrorMessage35_1": 308,
    "ErrorMessage36": 88,
    "ErrorMessage36_1": 313,
    "ErrorMessage37": 93,
    "ErrorMessage37_1": 318,
    "ErrorMessage38": 98,
    "ErrorMessage38_1": 323,
    "ErrorMessage39": 103,
    "ErrorMessage39_1": 328,
    "ErrorMessage4": 223,
    "ErrorMessage40": 108,
    "ErrorMessage40_1": 333,
    "ErrorMessage41": 113,
    "ErrorMessage41_1": 338,
    "ErrorMessage42": 118,
    "ErrorMessage42_1": 343,
    "ErrorMessage43": 393,
    "ErrorMessage44": 410,
    "ErrorMessage45": 421,
    "ErrorMessage46": 426,
    "ErrorMessage47": 454,
    "ErrorMessage48": 449,
    "ErrorMessage5": 228,
    "ErrorMessage6": 233,
    "ErrorMessage7": 238,
    "ErrorMessage8": 158,
    "ErrorMessage9": 163,
    "First Name_DataCard1": 154,
    "First Name_DataCard2": 24,
    "First Name_DataCard2_1": 249,
    "First Name_DataCard3": 397,
    "formAcknow": 9,
    "formEvent": 208,
    "formLongTerm": 123,
    "formReview": 18,
    "formReview_1": 243,
    "formSecurity": 368,
    "formVisitor": 153,
    "galleryCheckBox": 352,
    "galleryRequests": 356,
    "galleryTemplate1": 357,
    "galleryTemplate6": 353,
    "Group1": 1,
    "Header": 30,
    "Icon2_3": 470,
    "iconA_1": 497,
    "iconA_2": 491,
    "iconESI_1": 473,
    "iconLTAI_1": 483,
    "iconR_1": 490,
    "iconR_2": 484,
    "iconVI_1": 478,
    "Image1": 500,
    "Label1": 350,
    "Label2": 370,
    "Label2_1": 395,
    "Label2_3": 456,
    "Label2_4": 462,
    "Label2_5": 431,
    "labelAcknow": 8,
    "labelEvent": 207,
    "labelLongTerm": 122,
    "labelNewEventName_15": 480,
    "labelNewEventName_17": 486,
    "labelNewEventName_18": 487,
    "labelNewEventName_19": 493,
    "labelNewEventName_20": 494,
    "labelNewEventName_21": 498,
    "labelNewEventName_6": 475,
    "labelReview": 17,
    "labelReview_1": 242,
    "labelSecurity": 367,
    "labelVisitor": 152,
    "Last Name_DataCard1": 164,
    "Last Name_DataCard2": 34,
    "Last Name_DataCard2_1": 259,
    "Last Name_DataCard3": 403,
    "Loading Label": 2,
    "Middle Name_DataCard1": 159,
    "Middle Name_DataCard2": 29,
    "Middle Name_DataCard2_1": 254,
    "Middle Name_DataCard3": 400,
    "modalFloatRequest": 6,
    "modalFloatSecurity": 365,
    "modalRequest": 5,
    "modalSecurity": 364,
    "nextAcknow": 15,
    "NextArrow1": 359,
    "nextEvent": 240,
    "nextLongTerm": 150,
    "nextReview": 120,
    "nextReview_1": 345,
    "nextVisitor": 205,
    "pageAcknow": 7,
    "pageEvent": 206,
    "pageLongTerm": 121,
    "pageReview": 16,
    "pageReview_1": 241,
    "pageSecurity": 366,
    "pageVisitor": 151,
    "pbRequest": 346,
    "Rank/Grade_DataCard1": 184,
    "Rank/Grade_DataCard2": 69,
    "Rank/Grade_DataCard2_1": 294,
    "Rank/Grade_DataCard3": 406,
    "Rectangle2": 371,
    "Rectangle2_1": 396,
    "Rectangle2_3": 457,
    "Rectangle2_4": 463,
    "Rectangle2_5": 432,
    "rectangleNewEventNameStatusBar_11": 479,
    "rectangleNewEventNameStatusBar_12": 485,
    "rectangleNewEventNameStatusBar_13": 492,
    "rectangleNewEventNameStatusBar_5": 474,
    "Round Header": 499,
    "Screen1": 34,
    "screenPre": 142,
    "screenRequest": 147,
    "searchBarRequest": 348,
    "searchIconRequest": 347,
    "Separator1": 362,
    "Sponsor Phone Number_DataCard1": 229,
    "Sponsor Phone Number_DataCard2": 44,
    "Sponsor Phone Number_DataCard2_1": 269,
    "Sponsor Phone Number_DataCard3": 386,
    "Sponsor_DataCard1": 224,
    "Sponsor_DataCard2": 39,
    "Sponsor_DataCard2_1": 264,
    "Sponsor_DataCard3": 381,
    "StarVisible1": 11,
    "StarVisible10": 165,
    "StarVisible11": 185,
    "StarVisible12": 175,
    "StarVisible13": 180,
    "StarVisible14": 190,
    "StarVisible15": 195,
    "StarVisible16": 200,
    "StarVisible17": 125,
    "StarVisible18": 130,
    "StarVisible19": 135,
    "StarVisible2": 210,
    "StarVisible20": 140,
    "StarVisible21": 145,
    "StarVisible22": 170,
    "StarVisible23": 25,
    "StarVisible23_1": 250,
    "StarVisible24": 30,
    "StarVisible24_1": 255,
    "StarVisible25": 35,
    "StarVisible25_1": 260,
    "StarVisible26": 20,
    "StarVisible26_1": 245,
    "StarVisible27": 40,
    "StarVisible27_1": 265,
    "StarVisible28": 45,
    "StarVisible28_1": 270,
    "StarVisible29": 50,
    "StarVisible29_1": 275,
    "StarVisible3": 215,
    "StarVisible30": 55,
    "StarVisible30_1": 280,
    "StarVisible31": 60,
    "StarVisible31_1": 285,
    "StarVisible32": 65,
    "StarVisible32_1": 290,
    "StarVisible33": 70,
    "StarVisible33_1": 295,
    "StarVisible34": 75,
    "StarVisible34_1": 300,
    "StarVisible35": 80,
    "StarVisible35_1": 305,
    "StarVisible36": 85,
    "StarVisible36_1": 310,
    "StarVisible37": 90,
    "StarVisible37_1": 315,
    "StarVisible38": 95,
    "StarVisible38_1": 320,
    "StarVisible39": 100,
    "StarVisible39_1": 325,
    "StarVisible4": 220,
    "StarVisible40": 105,
    "StarVisible40_1": 330,
    "StarVisible41": 110,
    "StarVisible41_1": 335,
    "StarVisible42": 115,
    "StarVisible42_1": 340,
    "StarVisible43": 382,
    "StarVisible44": 390,
    "StarVisible45": 407,
    "StarVisible46": 418,
    "StarVisible47": 423,
    "StarVisible48": 451,
    "StarVisible49": 446,
    "StarVisible5": 225,
    "StarVisible6": 230,
    "StarVisible7": 235,
    "StarVisible8": 155,
    "StarVisible9": 160,
    "Subtitle1": 360,
    "timer": 3,
    "Title_DataCard1": 209,
    "Title_DataCard2": 19,
    "Title_DataCard2_1": 244,
    "Title_DataCard4": 372,
    "Title1": 358,
    "txt_Denied_3": 468,
    "Type of Visit_DataCard1": 189,
    "Type of Visit_DataCard2": 84,
    "Type of Visit_DataCard2_1": 309,
    "Type of Visit_DataCard3": 422,
    "Visit End Date_DataCard1": 219,
    "Visit End Date_DataCard2": 59,
    "Visit End Date_DataCard2_1": 284,
    "Visit End Date_DataCard3": 378,
    "Visit Start Date_DataCard1": 214,
    "Visit Start Date_DataCard2": 54,
    "Visit Start Date_DataCard2_1": 279,
    "Visit Start Date_DataCard3": 375
  },
  "ResourcesJsonIndices": {
    "Image-Marine Corps Tactical Systems Support Activity _MCTSSA": 1,
    "Image-SampleImage": 0
  },
  "RuleScreenIdWithoutScreen": {},
  "TemplateVersions": {},
  "VolatileProperties": {
    "AnalysisLoadTime": 3.8037476,
    "ControlCount": {
      "button": 6,
      "checkbox": 3,
      "circle": 5,
      "combobox": 37,
      "d5564032f2ee43308e8fdaf8819fb889": 2,
      "datepicker": 8,
      "dbd607af812e46be9d29858798df077d": 2,
      "dropdown": 1,
      "form": 7,
      "formViewer": 1,
      "gallery": 2,
      "galleryTemplate": 2,
      "group": 1,
      "groupContainer": 15,
      "icon": 25,
      "image": 1,
      "label": 317,
      "rectangle": 10,
      "screen": 3,
      "text": 39,
      "timer": 1,
      "toggleSwitch": 10,
      "typedDataCard": 111
    },
    "DeserializationLoadTime": 4.2038799,
    "ErrorCount": 4
  },
  "WasLocalDatabaseReferencesEmpty": true
}